{
  "guide_function_deepequal.md": "435a9fb3",
  "guide_started.md": "aa5baf1b",
  "guide_utils_object.md": "8325a264",
  "guide_element_event.md": "63dc5e1a",
  "guide_function_uuid.md": "ec1998e5",
  "guide_utils_is_type.md": "5ae3c34e",
  "guide_element_class.md": "7e941d9a",
  "guide_utils_is_regexp.md": "ea94482d",
  "guide_utils_formdata.md": "9c4f75fd",
  "guide_function_money.md": "f355425b",
  "guide_utils_date.md": "bc3ab473",
  "guide_function_color.md": "341cf2f8",
  "guide_window_storage.md": "8982d95f",
  "guide_function_mask.md": "719a1714",
  "index.md": "e16de70c",
  "guide_function_debouncethrottle.md": "f0308467",
  "guide_utils_string.md": "53919376",
  "guide_window_url.md": "78374c21",
  "guide_window_browser.md": "21ec727e",
  "guide_utils_file.md": "071fc7ca"
}
